runpycli/__init__.py
runpycli/analyzer.py
runpycli/click_helpers.py
runpycli/core.py
runpycli/group.py
runpycli/parsers.py
runpycli/pydantic_utils.py
runpycli/commands/__init__.py
runpycli/commands/docs.py
runpycli/commands/schema.py
runpycli-1.3.1.dist-info/licenses/LICENSE
runpycli-1.3.1.dist-info/METADATA
runpycli-1.3.1.dist-info/WHEEL
runpycli-1.3.1.dist-info/top_level.txt
runpycli-1.3.1.dist-info/RECORD
