Metadata-Version: 2.4
Name: runpycli
Version: 1.3.1
Summary: Convert Python functions to CLI commands automatically
Author-email: crimson206 <sisung.kim1@gmail.com>
Requires-Python: <4.0,>=3.10
License-File: LICENSE
Requires-Dist: pydantic<3.0.0,>=2.11.5
Requires-Dist: func-analyzer<0.2.0,>=0.1.1
Requires-Dist: click<9.0.0,>=8.2.1
Dynamic: license-file
